<annotation>
	<folder></folder>
	<filename>1277105327Image000011_jpg.rf.3e146f12f91aa2a1ce9efbd1e66b1893.jpg</filename>
	<path>1277105327Image000011_jpg.rf.3e146f12f91aa2a1ce9efbd1e66b1893.jpg</path>
	<source>
		<database>roboflow.ai</database>
	</source>
	<size>
		<width>1280</width>
		<height>960</height>
		<depth>3</depth>
	</size>
	<segmented>0</segmented>
	<object>
		<name>100_SIGN</name>
		<pose>Unspecified</pose>
		<truncated>0</truncated>
		<difficult>0</difficult>
		<occluded>0</occluded>
		<bndbox>
			<xmin>310</xmin>
			<xmax>332</xmax>
			<ymin>443</ymin>
			<ymax>464</ymax>
		</bndbox>
	</object>
	<object>
		<name>PRIORITY_ROAD</name>
		<pose>Unspecified</pose>
		<truncated>0</truncated>
		<difficult>0</difficult>
		<occluded>0</occluded>
		<bndbox>
			<xmin>266</xmin>
			<xmax>276</xmax>
			<ymin>464</ymin>
			<ymax>475</ymax>
		</bndbox>
	</object>
</annotation>
