<annotation>
	<folder></folder>
	<filename>1277108900Image000009_jpg.rf.7519248c85192c54263c354c046b9242.jpg</filename>
	<path>1277108900Image000009_jpg.rf.7519248c85192c54263c354c046b9242.jpg</path>
	<source>
		<database>roboflow.ai</database>
	</source>
	<size>
		<width>600</width>
		<height>450</height>
		<depth>3</depth>
	</size>
	<segmented>0</segmented>
	<object>
		<name>30_SIGN</name>
		<pose>Unspecified</pose>
		<truncated>0</truncated>
		<difficult>0</difficult>
		<occluded>0</occluded>
		<bndbox>
			<xmin>435</xmin>
			<xmax>441</xmax>
			<ymin>246</ymin>
			<ymax>260</ymax>
		</bndbox>
	</object>
	<object>
		<name>PEDESTRIAN_CROSSING</name>
		<pose>Unspecified</pose>
		<truncated>0</truncated>
		<difficult>0</difficult>
		<occluded>0</occluded>
		<bndbox>
			<xmin>225</xmin>
			<xmax>230</xmax>
			<ymin>269</ymin>
			<ymax>274</ymax>
		</bndbox>
	</object>
	<object>
		<name>PASS_RIGHT_SIDE</name>
		<pose>Unspecified</pose>
		<truncated>0</truncated>
		<difficult>0</difficult>
		<occluded>0</occluded>
		<bndbox>
			<xmin>225</xmin>
			<xmax>230</xmax>
			<ymin>274</ymin>
			<ymax>280</ymax>
		</bndbox>
	</object>
</annotation>
