<annotation>
	<folder></folder>
	<filename>1277107977Image000018_jpg.rf.3dafc69cf7b1e3b39b6dad5947e56ebb.jpg</filename>
	<path>1277107977Image000018_jpg.rf.3dafc69cf7b1e3b39b6dad5947e56ebb.jpg</path>
	<source>
		<database>roboflow.ai</database>
	</source>
	<size>
		<width>600</width>
		<height>450</height>
		<depth>3</depth>
	</size>
	<segmented>0</segmented>
	<object>
		<name>PEDESTRIAN_CROSSING</name>
		<pose>Unspecified</pose>
		<truncated>0</truncated>
		<difficult>0</difficult>
		<occluded>0</occluded>
		<bndbox>
			<xmin>481</xmin>
			<xmax>541</xmax>
			<ymin>118</ymin>
			<ymax>174</ymax>
		</bndbox>
	</object>
	<object>
		<name>NO_PARKING</name>
		<pose>Unspecified</pose>
		<truncated>0</truncated>
		<difficult>0</difficult>
		<occluded>0</occluded>
		<bndbox>
			<xmin>415</xmin>
			<xmax>430</xmax>
			<ymin>235</ymin>
			<ymax>251</ymax>
		</bndbox>
	</object>
	<object>
		<name>NO_PARKING</name>
		<pose>Unspecified</pose>
		<truncated>0</truncated>
		<difficult>0</difficult>
		<occluded>0</occluded>
		<bndbox>
			<xmin>268</xmin>
			<xmax>284</xmax>
			<ymin>241</ymin>
			<ymax>255</ymax>
		</bndbox>
	</object>
	<object>
		<name>WARNING</name>
		<pose>Unspecified</pose>
		<truncated>0</truncated>
		<difficult>0</difficult>
		<occluded>0</occluded>
		<bndbox>
			<xmin>227</xmin>
			<xmax>234</xmax>
			<ymin>267</ymin>
			<ymax>273</ymax>
		</bndbox>
	</object>
	<object>
		<name>PEDESTRIAN_CROSSING</name>
		<pose>Unspecified</pose>
		<truncated>0</truncated>
		<difficult>0</difficult>
		<occluded>0</occluded>
		<bndbox>
			<xmin>218</xmin>
			<xmax>222</xmax>
			<ymin>271</ymin>
			<ymax>274</ymax>
		</bndbox>
	</object>
</annotation>
