<annotation>
	<folder></folder>
	<filename>1277106257Image000056_jpg.rf.d103f21b42375f737a496b647fdd355e.jpg</filename>
	<path>1277106257Image000056_jpg.rf.d103f21b42375f737a496b647fdd355e.jpg</path>
	<source>
		<database>roboflow.ai</database>
	</source>
	<size>
		<width>1280</width>
		<height>960</height>
		<depth>3</depth>
	</size>
	<segmented>0</segmented>
	<object>
		<name>80_SIGN</name>
		<pose>Unspecified</pose>
		<truncated>0</truncated>
		<difficult>0</difficult>
		<occluded>0</occluded>
		<bndbox>
			<xmin>318</xmin>
			<xmax>330</xmax>
			<ymin>479</ymin>
			<ymax>490</ymax>
		</bndbox>
	</object>
	<object>
		<name>PRIORITY_ROAD</name>
		<pose>Unspecified</pose>
		<truncated>0</truncated>
		<difficult>0</difficult>
		<occluded>0</occluded>
		<bndbox>
			<xmin>320</xmin>
			<xmax>330</xmax>
			<ymin>489</ymin>
			<ymax>498</ymax>
		</bndbox>
	</object>
	<object>
		<name>STOP</name>
		<pose>Unspecified</pose>
		<truncated>0</truncated>
		<difficult>0</difficult>
		<occluded>0</occluded>
		<bndbox>
			<xmin>469</xmin>
			<xmax>485</xmax>
			<ymin>452</ymin>
			<ymax>478</ymax>
		</bndbox>
	</object>
</annotation>
