<annotation>
	<folder></folder>
	<filename>1277106794Image000041_jpg.rf.eacc9ea9014a7bf563262a11d1261416.jpg</filename>
	<path>1277106794Image000041_jpg.rf.eacc9ea9014a7bf563262a11d1261416.jpg</path>
	<source>
		<database>roboflow.ai</database>
	</source>
	<size>
		<width>600</width>
		<height>450</height>
		<depth>3</depth>
	</size>
	<segmented>0</segmented>
	<object>
		<name>GIVE_WAY</name>
		<pose>Unspecified</pose>
		<truncated>0</truncated>
		<difficult>0</difficult>
		<occluded>0</occluded>
		<bndbox>
			<xmin>409</xmin>
			<xmax>413</xmax>
			<ymin>192</ymin>
			<ymax>196</ymax>
		</bndbox>
	</object>
	<object>
		<name>PASS_RIGHT_SIDE</name>
		<pose>Unspecified</pose>
		<truncated>0</truncated>
		<difficult>0</difficult>
		<occluded>0</occluded>
		<bndbox>
			<xmin>408</xmin>
			<xmax>413</xmax>
			<ymin>196</ymin>
			<ymax>201</ymax>
		</bndbox>
	</object>
	<object>
		<name>PEDESTRIAN_CROSSING</name>
		<pose>Unspecified</pose>
		<truncated>0</truncated>
		<difficult>0</difficult>
		<occluded>0</occluded>
		<bndbox>
			<xmin>387</xmin>
			<xmax>393</xmax>
			<ymin>189</ymin>
			<ymax>195</ymax>
		</bndbox>
	</object>
	<object>
		<name>PEDESTRIAN_CROSSING</name>
		<pose>Unspecified</pose>
		<truncated>0</truncated>
		<difficult>0</difficult>
		<occluded>0</occluded>
		<bndbox>
			<xmin>487</xmin>
			<xmax>494</xmax>
			<ymin>195</ymin>
			<ymax>201</ymax>
		</bndbox>
	</object>
</annotation>
